[{"author": [{"family": "Cover", "given": "Thomas M"}, {"family": "Thomas", "given": "Joy A"}], "id": "coverELEMENTSINFORMATIONTHEORY", "language": "en-US", "title": "ELEMENTS OF INFORMATION THEORY", "type": "article-journal", "original_bibtex": "@article{coverELEMENTSINFORMATIONTHEORY,\n title = {{{ELEMENTS OF INFORMATION THEORY}}},\n author = {Cover, Thomas M and Thomas, Joy A},\n file = {/home/kellen/Zotero/storage/C6AJGW5I/Cover and Thomas - ELEMENTS OF INFORMATION THEORY.pdf},\n langid = {english}\n}\n"}]